ipug/__init__.py
ipug/cli.py
ipug/config.py
ipug/ipug.py
ipug-0.1.4.dist-info/AUTHORS.rst
ipug-0.1.4.dist-info/LICENSE
ipug-0.1.4.dist-info/METADATA
ipug-0.1.4.dist-info/WHEEL
ipug-0.1.4.dist-info/entry_points.txt
ipug-0.1.4.dist-info/top_level.txt
ipug-0.1.4.dist-info/RECORD
