Metadata-Version: 2.1
Name: ipug
Version: 0.1.4
Summary: iPug, the UDK Guide dog
Home-page: https://github.com/timotheuslin/ipug
Author: Timothy Lin
Author-email: timothy.gh.lin@gmail.com
License: BSD license
Keywords: ipug
Platform: UNKNOWN
Classifier: Development Status :: 2 - Pre-Alpha
Classifier: Intended Audience :: Developers
Classifier: License :: OSI Approved :: BSD License
Classifier: Natural Language :: English
Classifier: Programming Language :: Python :: 2
Classifier: Programming Language :: Python :: 2.7
Classifier: Programming Language :: Python :: 3
Classifier: Programming Language :: Python :: 3.6
Classifier: Programming Language :: Python :: 3.7
Requires-Dist: Click (>=6.0)
